Metadata-Version: 2.1
Name: test-the-best
Version: 5.0
Summary: Тест загрузки библиотеки
Author-email: neso_hoshi_official@mail.ru
Classifier: Programming Language :: Python :: 3
Classifier: License :: OSI Approved :: MIT License
Classifier: Operating System :: OS Independent
License-File: LICENSE
